estatpy/__init__.py
estatpy-0.1.1.dist-info/LICENSE
estatpy-0.1.1.dist-info/WHEEL
estatpy-0.1.1.dist-info/METADATA
estatpy-0.1.1.dist-info/RECORD
