Metadata-Version: 2.1
Name: estatpy
Version: 0.1.1
Summary: e-Stat API Client
Home-page: https://github.com/poyo46/estatpy
License: Apache-2.0
Keywords: e-Stat
Author: poyo46
Author-email: poyo4rock@gmail.com
Requires-Python: >=3.9,<4.0
Classifier: Development Status :: 3 - Alpha
Classifier: Intended Audience :: Developers
Classifier: License :: OSI Approved :: Apache Software License
Classifier: Operating System :: MacOS :: MacOS X
Classifier: Operating System :: Microsoft :: Windows
Classifier: Operating System :: POSIX :: Linux
Classifier: Programming Language :: Python :: 3
Classifier: Programming Language :: Python :: 3.7
Classifier: Programming Language :: Python :: 3.8
Classifier: Programming Language :: Python :: 3.9
Project-URL: Repository, https://github.com/poyo46/estatpy
